async_weather_sdk/__init__.py
async_weather_sdk/base.py
async_weather_sdk/qq.py
async_weather_sdk-0.1.1.dist-info/LICENSE
async_weather_sdk-0.1.1.dist-info/WHEEL
async_weather_sdk-0.1.1.dist-info/METADATA
async_weather_sdk-0.1.1.dist-info/RECORD
