Metadata-Version: 2.1
Name: async-weather-sdk
Version: 0.1.1
Summary: Async weather API wrapper for fetching weather and forecast data
Home-page: https://github.com/decentfox/async-weather-sdk
License: MIT
Keywords: weather,forecast,asyncio,python3
Author: DecentFoX
Author-email: service@decentfox.com
Requires-Python: >=3.6,<4.0
Classifier: Development Status :: 1 - Planning
Classifier: Framework :: AsyncIO
Classifier: Intended Audience :: Developers
Classifier: License :: OSI Approved :: MIT License
Classifier: Programming Language :: Python :: 3
Classifier: Programming Language :: Python :: 3.6
Classifier: Programming Language :: Python :: 3.7
Classifier: Programming Language :: Python :: 3.8
Requires-Dist: aiohttp[speedups] (>=3.6.2,<4.0.0)
Project-URL: Repository, https://github.com/decentfox/async-weather-sdk
